views_runs/__init__.py
views_runs/operations.py
views_runs/run.py
views_runs/run_result.py
views_runs/stats.py
views_runs/storage.py
views_runs/utilities.py
views_runs/validation.py
views_runs/vendoring.py
views_runs-1.14.2.dist-info/LICENSE
views_runs-1.14.2.dist-info/METADATA
views_runs-1.14.2.dist-info/WHEEL
views_runs-1.14.2.dist-info/RECORD
