Metadata-Version: 2.1
Name: views_runs
Version: 1.14.2
Summary: Tools for doing model runs with views
Home-page: https://www.github.com/prio-data/views_runs
License: CC-BY-NC
Author: peder2911
Author-email: pglandsverk@gmail.com
Requires-Python: >3.8,<3.15
Classifier: License :: Other/Proprietary License
Classifier: Programming Language :: Python :: 3
Classifier: Programming Language :: Python :: 3.9
Classifier: Programming Language :: Python :: 3.10
Classifier: Programming Language :: Python :: 3.11
Requires-Dist: scikit-learn (>=1.0.2,<2.0.0)
Requires-Dist: stepshift (>=2.2.1,<3.0.0)
Requires-Dist: views-partitioning (>=3.0.0,<4.0.0)
Requires-Dist: views-schema (>=2.2.0,<3.0.0)
Requires-Dist: viewser (>5.13.0,<7.0.0)
